odoo/addons/stock_orderpoint_move_link/README.rst
odoo/addons/stock_orderpoint_move_link/__init__.py
odoo/addons/stock_orderpoint_move_link/__manifest__.py
odoo/addons/stock_orderpoint_move_link/i18n/it.po
odoo/addons/stock_orderpoint_move_link/i18n/stock_orderpoint_move_link.pot
odoo/addons/stock_orderpoint_move_link/i18n/zh_CN.po
odoo/addons/stock_orderpoint_move_link/models/__init__.py
odoo/addons/stock_orderpoint_move_link/models/stock.py
odoo/addons/stock_orderpoint_move_link/models/stock_move.py
odoo/addons/stock_orderpoint_move_link/models/stock_warehouse_orderpoint.py
odoo/addons/stock_orderpoint_move_link/readme/CONTRIBUTORS.md
odoo/addons/stock_orderpoint_move_link/readme/DESCRIPTION.md
odoo/addons/stock_orderpoint_move_link/static/description/icon.png
odoo/addons/stock_orderpoint_move_link/static/description/index.html
odoo/addons/stock_orderpoint_move_link/tests/__init__.py
odoo/addons/stock_orderpoint_move_link/tests/test_stock_orderpoint_move_link.py
odoo/addons/stock_orderpoint_move_link/views/stock_move_views.xml
odoo_addon_stock_orderpoint_move_link-18.0.1.0.0.2.dist-info/METADATA
odoo_addon_stock_orderpoint_move_link-18.0.1.0.0.2.dist-info/WHEEL
odoo_addon_stock_orderpoint_move_link-18.0.1.0.0.2.dist-info/top_level.txt
odoo_addon_stock_orderpoint_move_link-18.0.1.0.0.2.dist-info/RECORD
